Test.v
module Test( // @[components.py:319:Test.fir@2.2]
  input         clock, // @[rawmodule.py:100:Test.fir@3.4]
  input         reset, // @[rawmodule.py:101:Test.fir@4.4]
  input  [31:0] io_a, // @[components.py:310:Test.fir@5.4]
  input  [31:0] io_b, // @[components.py:310:Test.fir@5.4]
  input  [1:0]  io_ctl, // @[components.py:310:Test.fir@5.4]
  output [31:0] io_out // @[components.py:310:Test.fir@5.4]
);
  wire [32:0] _T_8; // @[components.py:323:Test.fir@7.4]
  wire [32:0] _T_9; // @[components.py:324:Test.fir@8.4]
  wire [31:0] _T_10; // @[components.py:325:Test.fir@9.4]
  wire [31:0] _T_11; // @[components.py:326:Test.fir@10.4]
  wire  _T_12; // @[components.py:326:Test.fir@11.4]
  wire [32:0] _T_13; // @[components.py:326:Test.fir@12.4]
  wire  _T_14; // @[components.py:326:Test.fir@13.4]
  wire [32:0] _T_15; // @[components.py:326:Test.fir@14.4]
  wire  _T_16; // @[components.py:326:Test.fir@15.4]
  wire [32:0] _T_17; // @[components.py:326:Test.fir@16.4]
  wire  _T_18; // @[components.py:326:Test.fir@17.4]
  wire [32:0] _T_19; // @[components.py:326:Test.fir@18.4]
  assign _T_8 = io_a + io_b; // @[components.py:323:Test.fir@7.4]
  assign _T_9 = io_a - io_b; // @[components.py:324:Test.fir@8.4]
  assign _T_10 = io_a & io_b; // @[components.py:325:Test.fir@9.4]
  assign _T_11 = io_a | io_b; // @[components.py:326:Test.fir@10.4]
  assign _T_12 = io_ctl == 2'h0; // @[components.py:326:Test.fir@11.4]
  assign _T_13 = _T_12 ? _T_8 : 33'h0; // @[components.py:326:Test.fir@12.4]
  assign _T_14 = io_ctl == 2'h1; // @[components.py:326:Test.fir@13.4]
  assign _T_15 = _T_14 ? _T_9 : _T_13; // @[components.py:326:Test.fir@14.4]
  assign _T_16 = io_ctl == 2'h2; // @[components.py:326:Test.fir@15.4]
  assign _T_17 = _T_16 ? {{1'd0}, _T_10} : _T_15; // @[components.py:326:Test.fir@16.4]
  assign _T_18 = io_ctl == 2'h3; // @[components.py:326:Test.fir@17.4]
  assign _T_19 = _T_18 ? {{1'd0}, _T_11} : _T_17; // @[components.py:326:Test.fir@18.4]
  assign io_out = _T_19[31:0]; // @[components.py:326:Test.fir@19.4]
endmodule

Test.vcd
$version Generated by VerilatedVcd $end
$date Wed Jul  3 17:53:10 2019
 $end
$timescale   1ns $end

 $scope module TOP $end
  $var wire  1 # clock $end
  $var wire 32 % io_a [31:0] $end
  $var wire 32 & io_b [31:0] $end
  $var wire  2 ' io_ctl [1:0] $end
  $var wire 32 ( io_out [31:0] $end
  $var wire  1 $ reset $end
  $scope module Test $end
   $var wire  1 # clock $end
   $var wire 32 % io_a [31:0] $end
   $var wire 32 & io_b [31:0] $end
   $var wire  2 ' io_ctl [1:0] $end
   $var wire 32 ( io_out [31:0] $end
   $var wire  1 $ reset $end
  $upscope $end
 $upscope $end
$enddefinitions $end


#0
0#
0$
b00000000000000000000000000001010 %
b00000000000000000000000000000001 &
b00 '
b00000000000000000000000000001011 (
#1
b01 '
b00000000000000000000000000001001 (
#2
b10 '
b00000000000000000000000000000000 (
#3
b11 '
b00000000000000000000000000001011 (
#4
b00 '
b00000000000000000000000000000000 (
#5
b01 '
#6
b10 '
#7
b11 '
#8
b00 '
#9
b01 '
#10
b10 '
#11
b11 '
#12
b00 '
#13
b01 '
#14
b10 '
#15
b11 '
#16
b00 '
#17
b01 '
#18
b10 '
#19
b11 '
#20
b00 '
#21
b01 '
#22
b10 '
#23
b11 '
#24
b00 '
#25
b01 '
#26
b10 '
#27
b11 '
#28
b00 '
#29
b01 '
#30
b10 '
#31
b11 '
#32
b00 '
#33
b01 '
#34
b10 '
#35
b11 '
#36
b00 '
#37
b01 '
#38
b10 '
#39
b11 '
#40
b00 '
#41
b01 '
#42
b10 '
#43
b11 '
#44
b00 '
#45
b01 '
#46
b10 '
#47
b11 '
#48
b00 '
#49
b01 '
#50
b10 '
#51
b11 '
#52
b00 '
#53
b01 '
#54
b10 '
#55
b11 '
#56
b00 '
#57
b01 '
#58
b10 '
#59
b11 '
#60
b00 '
#61
b01 '
#62
b10 '
#63
b11 '
#64
b00 '
#65
b01 '
#66
b10 '
#67
b11 '
#68
b00 '
#69
b01 '
#70
b10 '
#71
b11 '
#72
b00 '
#73
b01 '
#74
b10 '
#75
b11 '
#76
b00 '
#77
b01 '
#78
b10 '
#79
b11 '
#80
b00 '
#81
b01 '
#82
b10 '
#83
b11 '
#84
b00 '
#85
b01 '
#86
b10 '
#87
b11 '
#88
b00 '
#89
b01 '
#90
b10 '
#91
b11 '
#92
b00 '
#93
b01 '
#94
b10 '
#95
b11 '
#96
b00 '
#97
b01 '
#98
b10 '
#99
b11 '
#100
b00 '
#101
b01 '
#102
b10 '
#103
b11 '
#104
b00 '
#105
b01 '
#106
b10 '
#107
b11 '
#108
b00 '
#109
b01 '
#110
b10 '
#111
b11 '
#112
b00 '
#113
b01 '
#114
b10 '
#115
b11 '
#116
b00 '
#117
b01 '
#118
b10 '
#119
b11 '
#120
b00 '
#121
b01 '
#122
b10 '
#123
b11 '
#124
b00 '
#125
b01 '
#126
b10 '
#127
b11 '
#128
b00 '
#129
b01 '
#130
b10 '
#131
b11 '
#132
b00 '
#133
b01 '
#134
b10 '
#135
b11 '
#136
b00 '
#137
b01 '
#138
b10 '
#139
b11 '
#140
b00 '
#141
b01 '
#142
b10 '
#143
b11 '
#144
b00 '
#145
b01 '
#146
b10 '
#147
b11 '
#148
b00 '
#149
b01 '
#150
b10 '
#151
b11 '
#152
b00 '
#153
b01 '
#154
b10 '
#155
b11 '
#156
b00 '
#157
b01 '
#158
b10 '
#159
b11 '
#160
b00 '
#161
b01 '
#162
b10 '
#163
b11 '
#164
b00 '
#165
b01 '
#166
b10 '
#167
b11 '
#168
b00 '
#169
b01 '
#170
b10 '
#171
b11 '
#172
b00 '
#173
b01 '
#174
b10 '
#175
b11 '
#176
b00 '
#177
b01 '
#178
b10 '
#179
b11 '
#180
b00 '
#181
b01 '
#182
b10 '
#183
b11 '
#184
b00 '
#185
b01 '
#186
b10 '
#187
b11 '
#188
b00 '
#189
b01 '
#190
b10 '
#191
b11 '
#192
b00 '
#193
b01 '
#194
b10 '
#195
b11 '
#196
b00 '
#197
b01 '
#198
b10 '
#199
b11 '
#200
b00 '
#201
b01 '
#202
b10 '
#203
b11 '
#204
b00 '
#205
b01 '
#206
b10 '
#207
b11 '
#208
b00 '
#209
b01 '
#210
b10 '
#211
b11 '
#212
b00 '
#213
b01 '
#214
b10 '
#215
b11 '
#216
b00 '
#217
b01 '
#218
b10 '
#219
b11 '
#220
b00 '
#221
b01 '
#222
b10 '
#223
b11 '
#224
b00 '
#225
b01 '
#226
b10 '
#227
b11 '
#228
b00 '
#229
b01 '
#230
b10 '
#231
b11 '
#232
b00 '
#233
b01 '
#234
b10 '
#235
b11 '
#236
b00 '
#237
b01 '
#238
b10 '
#239
b11 '
#240
b00 '
#241
b01 '
#242
b10 '
#243
b11 '
#244
b00 '
#245
b01 '
#246
b10 '
#247
b11 '
#248
b00 '
#249
b01 '
#250
b10 '
#251
b11 '
#252
b00 '
#253
b01 '
#254
b10 '
#255
b11 '
#256
b00 '
b00000000000000000000000000001011 (
#257
b01 '
b00000000000000000000000000001001 (
#258
b10 '
b00000000000000000000000000000000 (
#259
b11 '
b00000000000000000000000000001011 (
#260
b00 '
b00000000000000000000000000000000 (
#261
b01 '
#262
b10 '
#263
b11 '
#264
b00 '
#265
b01 '
#266
b10 '
#267
b11 '
#268
b00 '
#269
b01 '
#270
b10 '
#271
b11 '
#272
b00 '
#273
b01 '
#274
b10 '
#275
b11 '
#276
b00 '
#277
b01 '
#278
b10 '
#279
b11 '
#280
b00 '
#281
b01 '
#282
b10 '
#283
b11 '
#284
b00 '
#285
b01 '
#286
b10 '
#287
b11 '
#288
b00 '
#289
b01 '
#290
b10 '
#291
b11 '
#292
b00 '
#293
b01 '
#294
b10 '
#295
b11 '
#296
b00 '
#297
b01 '
#298
b10 '
#299
b11 '
#300
b00 '
#301
b01 '
#302
b10 '
#303
b11 '
#304
b00 '
#305
b01 '
#306
b10 '
#307
b11 '
#308
b00 '
#309
b01 '
#310
b10 '
#311
b11 '
#312
b00 '
#313
b01 '
#314
b10 '
#315
b11 '
#316
b00 '
#317
b01 '
#318
b10 '
#319
b11 '
#320
b00 '
#321
b01 '
#322
b10 '
#323
b11 '
#324
b00 '
#325
b01 '
#326
b10 '
#327
b11 '
#328
b00 '
#329
b01 '
#330
b10 '
#331
b11 '
#332
b00 '
#333
b01 '
#334
b10 '
#335
b11 '
#336
b00 '
#337
b01 '
#338
b10 '
#339
b11 '
#340
b00 '
#341
b01 '
#342
b10 '
#343
b11 '
#344
b00 '
#345
b01 '
#346
b10 '
#347
b11 '
#348
b00 '
#349
b01 '
#350
b10 '
#351
b11 '
#352
b00 '
#353
b01 '
#354
b10 '
#355
b11 '
#356
b00 '
#357
b01 '
#358
b10 '
#359
b11 '
#360
b00 '
#361
b01 '
#362
b10 '
#363
b11 '
#364
b00 '
#365
b01 '
#366
b10 '
#367
b11 '
#368
b00 '
#369
b01 '
#370
b10 '
#371
b11 '
#372
b00 '
#373
b01 '
#374
b10 '
#375
b11 '
#376
b00 '
#377
b01 '
#378
b10 '
#379
b11 '
#380
b00 '
#381
b01 '
#382
b10 '
#383
b11 '
#384
b00 '
#385
b01 '
#386
b10 '
#387
b11 '
#388
b00 '
#389
b01 '
#390
b10 '
#391
b11 '
#392
b00 '
#393
b01 '
#394
b10 '
#395
b11 '
#396
b00 '
#397
b01 '
#398
b10 '
#399
b11 '
#400
b00 '
#401
b01 '
#402
b10 '
#403
b11 '
#404
b00 '
#405
b01 '
#406
b10 '
#407
b11 '
#408
b00 '
#409
b01 '
#410
b10 '
#411
b11 '
#412
b00 '
#413
b01 '
#414
b10 '
#415
b11 '
#416
b00 '
#417
b01 '
#418
b10 '
#419
b11 '
#420
b00 '
#421
b01 '
#422
b10 '
#423
b11 '
#424
b00 '
#425
b01 '
#426
b10 '
#427
b11 '
#428
b00 '
#429
b01 '
#430
b10 '
#431
b11 '
#432
b00 '
#433
b01 '
#434
b10 '
#435
b11 '
#436
b00 '
#437
b01 '
#438
b10 '
#439
b11 '
#440
b00 '
#441
b01 '
#442
b10 '
#443
b11 '
#444
b00 '
#445
b01 '
#446
b10 '
#447
b11 '
#448
b00 '
#449
b01 '
#450
b10 '
#451
b11 '
#452
b00 '
#453
b01 '
#454
b10 '
#455
b11 '
#456
b00 '
#457
b01 '
#458
b10 '
#459
b11 '
#460
b00 '
#461
b01 '
#462
b10 '
#463
b11 '
#464
b00 '
#465
b01 '
#466
b10 '
#467
b11 '
#468
b00 '
#469
b01 '
#470
b10 '
#471
b11 '
#472
b00 '
#473
b01 '
#474
b10 '
#475
b11 '
#476
b00 '
#477
b01 '
#478
b10 '
#479
b11 '
#480
b00 '
#481
b01 '
#482
b10 '
#483
b11 '
#484
b00 '
#485
b01 '
#486
b10 '
#487
b11 '
#488
b00 '
#489
b01 '
#490
b10 '
#491
b11 '
#492
b00 '
#493
b01 '
#494
b10 '
#495
b11 '
#496
b00 '
#497
b01 '
#498
b10 '
#499
b11 '
#500
b00 '
#501
b01 '
#502
b10 '
#503
b11 '
#504
b00 '
#505
b01 '
#506
b10 '
#507
b11 '
#508
b00 '
#509
b01 '
#510
b10 '
#511
b11 '
#512
b00 '
b00000000000000000000000000001011 (
#513
b01 '
b00000000000000000000000000001001 (
#514
b10 '
b00000000000000000000000000000000 (
#515
b11 '
b00000000000000000000000000001011 (
#516
b00 '
b00000000000000000000000000000000 (
#517
b01 '
#518
b10 '
#519
b11 '
#520
b00 '
#521
b01 '
#522
b10 '
#523
b11 '
#524
b00 '
#525
b01 '
#526
b10 '
#527
b11 '
#528
b00 '
#529
b01 '
#530
b10 '
#531
b11 '
#532
b00 '
#533
b01 '
#534
b10 '
#535
b11 '
#536
b00 '
#537
b01 '
#538
b10 '
#539
b11 '
#540
b00 '
#541
b01 '
#542
b10 '
#543
b11 '
#544
b00 '
#545
b01 '
#546
b10 '
#547
b11 '
#548
b00 '
#549
b01 '
#550
b10 '
#551
b11 '
#552
b00 '
#553
b01 '
#554
b10 '
#555
b11 '
#556
b00 '
#557
b01 '
#558
b10 '
#559
b11 '
#560
b00 '
#561
b01 '
#562
b10 '
#563
b11 '
#564
b00 '
#565
b01 '
#566
b10 '
#567
b11 '
#568
b00 '
#569
b01 '
#570
b10 '
#571
b11 '
#572
b00 '
#573
b01 '
#574
b10 '
#575
b11 '
#576
b00 '
#577
b01 '
#578
b10 '
#579
b11 '
#580
b00 '
#581
b01 '
#582
b10 '
#583
b11 '
#584
b00 '
#585
b01 '
#586
b10 '
#587
b11 '
#588
b00 '
#589
b01 '
#590
b10 '
#591
b11 '
#592
b00 '
#593
b01 '
#594
b10 '
#595
b11 '
#596
b00 '
#597
b01 '
#598
b10 '
#599
b11 '
#600
b00 '
#601
b01 '
#602
b10 '
#603
b11 '
#604
b00 '
#605
b01 '
#606
b10 '
#607
b11 '
#608
b00 '
#609
b01 '
#610
b10 '
#611
b11 '
#612
b00 '
#613
b01 '
#614
b10 '
#615
b11 '
#616
b00 '
#617
b01 '
#618
b10 '
#619
b11 '
#620
b00 '
#621
b01 '
#622
b10 '
#623
b11 '
#624
b00 '
#625
b01 '
#626
b10 '
#627
b11 '
#628
b00 '
#629
b01 '
#630
b10 '
#631
b11 '
#632
b00 '
#633
b01 '
#634
b10 '
#635
b11 '
#636
b00 '
#637
b01 '
#638
b10 '
#639
b11 '
#640
b00 '
#641
b01 '
#642
b10 '
#643
b11 '
#644
b00 '
#645
b01 '
#646
b10 '
#647
b11 '
#648
b00 '
#649
b01 '
#650
b10 '
#651
b11 '
#652
b00 '
#653
b01 '
#654
b10 '
#655
b11 '
#656
b00 '
#657
b01 '
#658
b10 '
#659
b11 '
#660
b00 '
#661
b01 '
#662
b10 '
#663
b11 '
#664
b00 '
#665
b01 '
#666
b10 '
#667
b11 '
#668
b00 '
#669
b01 '
#670
b10 '
#671
b11 '
#672
b00 '
#673
b01 '
#674
b10 '
#675
b11 '
#676
b00 '
#677
b01 '
#678
b10 '
#679
b11 '
#680
b00 '
#681
b01 '
#682
b10 '
#683
b11 '
#684
b00 '
#685
b01 '
#686
b10 '
#687
b11 '
#688
b00 '
#689
b01 '
#690
b10 '
#691
b11 '
#692
b00 '
#693
b01 '
#694
b10 '
#695
b11 '
#696
b00 '
#697
b01 '
#698
b10 '
#699
b11 '
#700
b00 '
#701
b01 '
#702
b10 '
#703
b11 '
#704
b00 '
#705
b01 '
#706
b10 '
#707
b11 '
#708
b00 '
#709
b01 '
#710
b10 '
#711
b11 '
#712
b00 '
#713
b01 '
#714
b10 '
#715
b11 '
#716
b00 '
#717
b01 '
#718
b10 '
#719
b11 '
#720
b00 '
#721
b01 '
#722
b10 '
#723
b11 '
#724
b00 '
#725
b01 '
#726
b10 '
#727
b11 '
#728
b00 '
#729
b01 '
#730
b10 '
#731
b11 '
#732
b00 '
#733
b01 '
#734
b10 '
#735
b11 '
#736
b00 '
#737
b01 '
#738
b10 '
#739
b11 '
#740
b00 '
#741
b01 '
#742
b10 '
#743
b11 '
#744
b00 '
#745
b01 '
#746
b10 '
#747
b11 '
#748
b00 '
#749
b01 '
#750
b10 '
#751
b11 '
#752
b00 '
#753
b01 '
#754
b10 '
#755
b11 '
#756
b00 '
#757
b01 '
#758
b10 '
#759
b11 '
#760
b00 '
#761
b01 '
#762
b10 '
#763
b11 '
#764
b00 '
#765
b01 '
#766
b10 '
#767
b11 '
#768
b00 '
b00000000000000000000000000001011 (
#769
b01 '
b00000000000000000000000000001001 (
#770
b10 '
b00000000000000000000000000000000 (
#771
b11 '
b00000000000000000000000000001011 (
#772
b00 '
b00000000000000000000000000000000 (
#773
b01 '
#774
b10 '
#775
b11 '
#776
b00 '
#777
b01 '
#778
b10 '
#779
b11 '
#780
b00 '
#781
b01 '
#782
b10 '
#783
b11 '
#784
b00 '
#785
b01 '
#786
b10 '
#787
b11 '
#788
b00 '
#789
b01 '
#790
b10 '
#791
b11 '
#792
b00 '
#793
b01 '
#794
b10 '
#795
b11 '
#796
b00 '
#797
b01 '
#798
b10 '
#799
b11 '
#800
b00 '
#801
b01 '
#802
b10 '
#803
b11 '
#804
b00 '
#805
b01 '
#806
b10 '
#807
b11 '
#808
b00 '
#809
b01 '
#810
b10 '
#811
b11 '
#812
b00 '
#813
b01 '
#814
b10 '
#815
b11 '
#816
b00 '
#817
b01 '
#818
b10 '
#819
b11 '
#820
b00 '
#821
b01 '
#822
b10 '
#823
b11 '
#824
b00 '
#825
b01 '
#826
b10 '
#827
b11 '
#828
b00 '
#829
b01 '
#830
b10 '
#831
b11 '
#832
b00 '
#833
b01 '
#834
b10 '
#835
b11 '
#836
b00 '
#837
b01 '
#838
b10 '
#839
b11 '
#840
b00 '
#841
b01 '
#842
b10 '
#843
b11 '
#844
b00 '
#845
b01 '
#846
b10 '
#847
b11 '
#848
b00 '
#849
b01 '
#850
b10 '
#851
b11 '
#852
b00 '
#853
b01 '
#854
b10 '
#855
b11 '
#856
b00 '
#857
b01 '
#858
b10 '
#859
b11 '
#860
b00 '
#861
b01 '
#862
b10 '
#863
b11 '
#864
b00 '
#865
b01 '
#866
b10 '
#867
b11 '
#868
b00 '
#869
b01 '
#870
b10 '
#871
b11 '
#872
b00 '
#873
b01 '
#874
b10 '
#875
b11 '
#876
b00 '
#877
b01 '
#878
b10 '
#879
b11 '
#880
b00 '
#881
b01 '
#882
b10 '
#883
b11 '
#884
b00 '
#885
b01 '
#886
b10 '
#887
b11 '
#888
b00 '
#889
b01 '
#890
b10 '
#891
b11 '
#892
b00 '
#893
b01 '
#894
b10 '
#895
b11 '
#896
b00 '
#897
b01 '
#898
b10 '
#899
b11 '
#900
b00 '
#901
b01 '
#902
b10 '
#903
b11 '
#904
b00 '
#905
b01 '
#906
b10 '
#907
b11 '
#908
b00 '
#909
b01 '
#910
b10 '
#911
b11 '
#912
b00 '
#913
b01 '
#914
b10 '
#915
b11 '
#916
b00 '
#917
b01 '
#918
b10 '
#919
b11 '
#920
b00 '
#921
b01 '
#922
b10 '
#923
b11 '
#924
b00 '
#925
b01 '
#926
b10 '
#927
b11 '
#928
b00 '
#929
b01 '
#930
b10 '
#931
b11 '
#932
b00 '
#933
b01 '
#934
b10 '
#935
b11 '
#936
b00 '
#937
b01 '
#938
b10 '
#939
b11 '
#940
b00 '
#941
b01 '
#942
b10 '
#943
b11 '
#944
b00 '
#945
b01 '
#946
b10 '
#947
b11 '
#948
b00 '
#949
b01 '
#950
b10 '
#951
b11 '
#952
b00 '
#953
b01 '
#954
b10 '
#955
b11 '
#956
b00 '
#957
b01 '
#958
b10 '
#959
b11 '
#960
b00 '
#961
b01 '
#962
b10 '
#963
b11 '
#964
b00 '
#965
b01 '
#966
b10 '
#967
b11 '
#968
b00 '
#969
b01 '
#970
b10 '
#971
b11 '
#972
b00 '
#973
b01 '
#974
b10 '
#975
b11 '
#976
b00 '
#977
b01 '
#978
b10 '
#979
b11 '
#980
b00 '
#981
b01 '
#982
b10 '
#983
b11 '
#984
b00 '
#985
b01 '
#986
b10 '
#987
b11 '
#988
b00 '
#989
b01 '
#990
b10 '
#991
b11 '
#992
b00 '
#993
b01 '
#994
b10 '
#995
b11 '
#996
b00 '
#997
b01 '
#998
b10 '
#999
b11 '
#1000
b00 '
#1001
b01 '
#1002
b10 '
#1003
b11 '
#1004
b00 '
#1005
b01 '
#1006
b10 '
#1007
b11 '
#1008
b00 '
#1009
b01 '
#1010
b10 '
#1011
b11 '
#1012
b00 '
#1013
b01 '
#1014
b10 '
#1015
b11 '
#1016
b00 '
#1017
b01 '
#1018
b10 '
#1019
b11 '
#1020
b00 '
#1021
b01 '
#1022
b10 '
#1023
b11 '
