Decoder.v
module Decoder(
    input reset,
    input [2:0] S,
    output [7:0] out
);
    always @*
    begin
        if(reset == 1'b1)
            out = 8'b00000000;
        else
        begin
            case(S)
                3'b000: out = 8'b00000001;
                3'b001: out = 8'b00000010;
                3'b010: out = 8'b00000100;
                3'b011: out = 8'b00001000;
                3'b100: out = 8'b00010000;
                3'b101: out = 8'b00100000;
                3'b110: out = 8'b01000000;
                3'b111: out = 8'b10000000;
            endcase
        end
    end
endmodule

pipe/Decoder.vcd
$version Generated by VerilatedVcd $end
$date Wed Jul 24 17:04:43 2019
 $end
$timescale   1ns $end

 $scope module TOP $end
  $var wire  3 $ S [2:0] $end
  $var wire  8 % out [7:0] $end
  $var wire  1 # reset $end
  $scope module Decoder $end
   $var wire  3 $ S [2:0] $end
   $var wire  8 % out [7:0] $end
   $var wire  1 # reset $end
  $upscope $end
 $upscope $end
$enddefinitions $end


#0
0#
b000 $
b00000001 %
#1
#2
b001 $
b00000010 %
#3
b010 $
b00000100 %
#4
b011 $
b00001000 %
#5
b100 $
b00010000 %
#6
b101 $
b00100000 %
#7
b110 $
b01000000 %
#8
b111 $
b10000000 %
#9
b000 $
b00000001 %
#10
b001 $
b00000010 %
#11
b010 $
b00000100 %
#12
b011 $
b00001000 %
#13
b100 $
b00010000 %
#14
b101 $
b00100000 %
#15
b110 $
b01000000 %
#16
b111 $
b10000000 %
#17
b000 $
b00000001 %
#18
b001 $
b00000010 %
#19
b010 $
b00000100 %
#20
b011 $
b00001000 %
#21
b100 $
b00010000 %
#22
b101 $
b00100000 %
#23
b110 $
b01000000 %
#24
b111 $
b10000000 %
#25
b000 $
b00000001 %
#26
b001 $
b00000010 %
#27
b010 $
b00000100 %
#28
b011 $
b00001000 %
#29
b100 $
b00010000 %
#30
b101 $
b00100000 %
#31
b110 $
b01000000 %
#32
b111 $
b10000000 %
#33
b000 $
b00000001 %
#34
b001 $
b00000010 %
#35
b010 $
b00000100 %
#36
b011 $
b00001000 %
#37
b100 $
b00010000 %
#38
b101 $
b00100000 %
#39
b110 $
b01000000 %
#40
b111 $
b10000000 %
#41
b000 $
b00000001 %
#42
b001 $
b00000010 %
#43
b010 $
b00000100 %
#44
b011 $
b00001000 %
#45
b100 $
b00010000 %
#46
b101 $
b00100000 %
#47
b110 $
b01000000 %
#48
b111 $
b10000000 %
#49
b000 $
b00000001 %
#50
b001 $
b00000010 %
#51
b010 $
b00000100 %
#52
b011 $
b00001000 %
#53
b100 $
b00010000 %
#54
b101 $
b00100000 %
#55
b110 $
b01000000 %
#56
b111 $
b10000000 %
#57
b000 $
b00000001 %
#58
b001 $
b00000010 %
#59
b010 $
b00000100 %
#60
b011 $
b00001000 %
#61
b100 $
b00010000 %
#62
b101 $
b00100000 %
#63
b110 $
b01000000 %
#64
b111 $
b10000000 %
#65
b000 $
b00000001 %
#66
b001 $
b00000010 %
#67
b010 $
b00000100 %
#68
b011 $
b00001000 %
#69
b100 $
b00010000 %
#70
b101 $
b00100000 %
#71
b110 $
b01000000 %
#72
b111 $
b10000000 %
#73
b000 $
b00000001 %
#74
b001 $
b00000010 %
#75
b010 $
b00000100 %
#76
b011 $
b00001000 %
#77
b100 $
b00010000 %
#78
b101 $
b00100000 %
#79
b110 $
b01000000 %
#80
b111 $
b10000000 %
#81
b000 $
b00000001 %
#82
b001 $
b00000010 %
#83
b010 $
b00000100 %
#84
b011 $
b00001000 %
#85
b100 $
b00010000 %
#86
b101 $
b00100000 %
#87
b110 $
b01000000 %
#88
b111 $
b10000000 %
#89
b000 $
b00000001 %
#90
b001 $
b00000010 %
#91
b010 $
b00000100 %
#92
b011 $
b00001000 %
#93
b100 $
b00010000 %
#94
b101 $
b00100000 %
#95
b110 $
b01000000 %
#96
b111 $
b10000000 %
#97
b000 $
b00000001 %
#98
b001 $
b00000010 %
#99
b010 $
b00000100 %
#100
b011 $
b00001000 %
